LimeNDAdecoder/__init__.py
LimeNDAdecoder/nda_functions.py
LimeNDAdecoder/nda_version_8_0.py
LimeNDAdecoder-1.3.0.dist-info/METADATA
LimeNDAdecoder-1.3.0.dist-info/WHEEL
LimeNDAdecoder-1.3.0.dist-info/top_level.txt
LimeNDAdecoder-1.3.0.dist-info/RECORD
