Metadata-Version: 2.1
Name: LimeNDAdecoder
Version: 1.3.0
Summary: Python Package for working with NDA files, specifically for people at Lime.AI
Author-email: Lime AI Celltesting <celltesting@lime.ai>
Project-URL: Homepage, https://github.com/limeaicell/LimeNDAdecoder
Project-URL: Bug Tracker, https://github.com/limeaicell/LimeNDAdecoder/issues
Classifier: Programming Language :: Python :: 3
Classifier: Operating System :: OS Independent
Requires-Python: >=3.8
Requires-Dist: numpy
Requires-Dist: pandas
Requires-Dist: xlsxwriter
